psmatching/.DS_Store
psmatching/__init__.py
psmatching/match.py
psmatching/run.py
psmatching/utilities.py
psmatching-0.1.dev21.dist-info/METADATA
psmatching-0.1.dev21.dist-info/WHEEL
psmatching-0.1.dev21.dist-info/top_level.txt
psmatching-0.1.dev21.dist-info/RECORD
