Metadata-Version: 2.1
Name: psmatching
Version: 0.1.dev21
Summary: Propensity score matching
Home-page: http://www.github.com/rlirey/psmatching
Author: Ryan L. Irey
Author-email: ireyx001@umn.edu
License: Apache 2.0 License
Download-URL: http://www.github.com/rlirey/psmatching
Platform: UNKNOWN
Classifier: Development Status :: 3 - Alpha
Classifier: Environment :: Console
Classifier: Intended Audience :: Developers
Classifier: Intended Audience :: Science/Research
Classifier: License :: OSI Approved :: Apache Software License
Classifier: Programming Language :: Python :: 3
Classifier: Topic :: Scientific/Engineering
Classifier: Operating System :: Microsoft :: Windows
Classifier: Operating System :: POSIX
Classifier: Operating System :: Unix
Classifier: Operating System :: MacOS
Requires-Dist: numpy
Requires-Dist: pandas
Requires-Dist: scipy
Requires-Dist: statsmodels
